wide_product-0.1.1.dist-info/top_level.txt
wide_product-0.1.1.dist-info/WHEEL
wide_product-0.1.1.dist-info/COPYING
wide_product-0.1.1.dist-info/RECORD
wide_product-0.1.1.dist-info/METADATA
wide_product/_wide.abi3.so
wide_product/wide.py
wide_product/__init__.py
