Metadata-Version: 2.1
Name: wide-product
Version: 0.1.1
Summary: Wide (partial Khatri-Rao) sparse matrix product
Home-page: https://github.com/thread/wide-product
Author: Thread Tech
Author-email: tech@thread.com
License: MIT
Keywords: numpy,scipy,matrix,sparse,khatri-rao,product,science,feature,courgette
Classifier: Development Status :: 3 - Alpha
Classifier: Intended Audience :: Developers
Classifier: Intended Audience :: Science/Research
Classifier: License :: OSI Approved :: MIT License
Classifier: Natural Language :: English
Classifier: Operating System :: POSIX
Classifier: Programming Language :: Python
Classifier: Programming Language :: Python :: 3.6
Classifier: Programming Language :: Python :: 3.7
Classifier: Programming Language :: Python :: 3.8
Classifier: Programming Language :: Python :: 3.9
Classifier: Programming Language :: Python :: 3.10
Classifier: Programming Language :: Python :: 3.11
Classifier: Topic :: Scientific/Engineering
Classifier: Topic :: Scientific/Engineering :: Information Analysis
Classifier: Topic :: Scientific/Engineering :: Mathematics
Classifier: Topic :: Software Development :: Libraries
Requires-Python: >=3.7
License-File: COPYING
Requires-Dist: cffi
Requires-Dist: numpy
Requires-Dist: scipy
